voiceconversion/Exceptions.py
voiceconversion/IORecorder.py
voiceconversion/VoiceChangerV2.py
voiceconversion/__init__.py
voiceconversion/const.py
voiceconversion/imported_model_info_manager.py
voiceconversion/voice_changer_settings.py
voiceconversion/Local/AudioDeviceList.py
voiceconversion/Local/ServerAudio.py
voiceconversion/RVC/RVCr2.py
voiceconversion/RVC/consts.py
voiceconversion/RVC/rvc_model_importer.py
voiceconversion/RVC/rvc_model_merger.py
voiceconversion/RVC/inferencer/Inferencer.py
voiceconversion/RVC/inferencer/InferencerManager.py
voiceconversion/RVC/inferencer/OnnxRVCInferencer.py
voiceconversion/RVC/inferencer/OnnxRVCInferencerNono.py
voiceconversion/RVC/inferencer/RVCInferencer.py
voiceconversion/RVC/inferencer/RVCInferencerNono.py
voiceconversion/RVC/inferencer/RVCInferencerv2.py
voiceconversion/RVC/inferencer/RVCInferencerv2Nono.py
voiceconversion/RVC/inferencer/WebUIInferencer.py
voiceconversion/RVC/inferencer/WebUIInferencerNono.py
voiceconversion/RVC/inferencer/rvc_models/infer_pack/attentions.py
voiceconversion/RVC/inferencer/rvc_models/infer_pack/attentions_onnx.py
voiceconversion/RVC/inferencer/rvc_models/infer_pack/commons.py
voiceconversion/RVC/inferencer/rvc_models/infer_pack/models.py
voiceconversion/RVC/inferencer/rvc_models/infer_pack/models_onnx.py
voiceconversion/RVC/inferencer/rvc_models/infer_pack/modules.py
voiceconversion/RVC/inferencer/rvc_models/infer_pack/transforms.py
voiceconversion/RVC/model_merger/merge_model.py
voiceconversion/RVC/onnx_exporter/export2onnx.py
voiceconversion/RVC/pipeline/Pipeline.py
voiceconversion/RVC/pipeline/PipelineGenerator.py
voiceconversion/common/FCPE.py
voiceconversion/common/MelExtractor.py
voiceconversion/common/MelExtractorFcpe.py
voiceconversion/common/OnnxLoader.py
voiceconversion/common/STFT.py
voiceconversion/common/SafetensorsUtils.py
voiceconversion/common/TorchUtils.py
voiceconversion/common/deviceManager/DeviceManager.py
voiceconversion/common/deviceManager/DummyDML.py
voiceconversion-0.0.8.dist-info/licenses/LICENSE
voiceconversion-0.0.8.dist-info/METADATA
voiceconversion-0.0.8.dist-info/WHEEL
voiceconversion-0.0.8.dist-info/top_level.txt
voiceconversion-0.0.8.dist-info/RECORD
