Metadata-Version: 2.4
Name: voiceconversion
Version: 0.0.8
Summary: Speech-to-speech conversion
Author-email: develOseven <devel.oseven@gmail.com>
License-Expression: MIT
Project-URL: Homepage, https://github.com/develOseven/voiceconversion
Project-URL: Issues, https://github.com/develOseven/voiceconversion/issues
Classifier: Programming Language :: Python :: 3
Classifier: Operating System :: OS Independent
Requires-Python: ==3.12.3
License-File: LICENSE
Requires-Dist: msvc-runtime>=14.38; sys_platform == "win32"
Requires-Dist: numpy
Requires-Dist: scipy
Requires-Dist: librosa
Requires-Dist: sounddevice<0.5.0
Requires-Dist: python-dotenv
Requires-Dist: pydantic-settings
Requires-Dist: xxhash
Requires-Dist: torch
Requires-Dist: torchaudio
Requires-Dist: faiss-cpu; sys_platform != "linux"
Requires-Dist: faiss-gpu-cu12; sys_platform == "linux"
Requires-Dist: onnxscript
Requires-Dist: onnxsim
Requires-Dist: onnxruntime-gpu
Requires-Dist: torchcrepe
Requires-Dist: torchfcpe
Requires-Dist: safetensors
Requires-Dist: aiohttp
Provides-Extra: dev
Requires-Dist: pytest; extra == "dev"
Dynamic: license-file
